Metadata-Version: 2.1
Name: breakSeqInNs-then-translate
Version: 0.0.1
Summary: To filter the sequences by translating the protein coding genes (PCGs) with proper genetic code table, if one of the PCGs has interal stop codon, filter out this sequence. See https://github.com/linzhi2013/breakSeqInNs_then_translate
Home-page: https://github.com/linzhi2013/breakSeqInNs_then_translate
Author: Guanliang Meng
Author-email: mengguanliang@foxmail.com
License: UNKNOWN
Platform: UNKNOWN
Classifier: Development Status :: 3 - Alpha
Classifier: Intended Audience :: Science/Research
Classifier: Topic :: Scientific/Engineering :: Bio-Informatics
Classifier: License :: OSI Approved :: GNU General Public License v3 or later (GPLv3+)
Classifier: Programming Language :: Python :: 3
Classifier: Operating System :: MacOS :: MacOS X
Classifier: Operating System :: Microsoft :: Windows
Classifier: Operating System :: POSIX :: Linux
Requires-Python: >=3
